fran/__init__.py
fran/__main__.py
fran/common.py
fran/config.toml
fran/constants.py
fran/controls.txt
fran/events.py
fran/frames.py
fran/gui.py
fran/rename.py
fran-0.9.1.dist-info/LICENSE
fran-0.9.1.dist-info/METADATA
fran-0.9.1.dist-info/WHEEL
fran-0.9.1.dist-info/entry_points.txt
fran-0.9.1.dist-info/top_level.txt
fran-0.9.1.dist-info/RECORD
