Metadata-Version: 2.1
Name: fran
Version: 0.9.1
Summary: Annotate frames of a multiTIFF video
Home-page: https://github.com/clbarnes/frame_annotator
Author: Chris L. Barnes
Author-email: barnesc@janelia.hhmi.org
License: MIT
Platform: UNKNOWN
Requires-Python: >=3.7
Requires-Dist: imageio (>=2.5.0)
Requires-Dist: pygame (>=1.9.5)
Requires-Dist: pandas (>=0.24.2)
Requires-Dist: numpy (>=1.16.2)
Requires-Dist: scikit-image (>=0.15.0)
Requires-Dist: toml (>=0.10.0)
